Metadata-Version: 2.1
Name: sphinxcontrib-googleanalytics-workaround
Version: 0.2.dev20231020
Summary: Sphinx extension googleanalytics
Home-page: https://github.com/sphinx-contrib/googleanalytics
Download-URL: http://pypi.python.org/pypi/sphinxcontrib-googleanalytics
Author: Domen Kozar
Author-email: domen@dev.si
License: BSD
Platform: any
Classifier: Development Status :: 4 - Beta
Classifier: Environment :: Console
Classifier: Environment :: Web Environment
Classifier: Intended Audience :: Developers
Classifier: License :: OSI Approved :: BSD License
Classifier: Operating System :: OS Independent
Classifier: Programming Language :: Python
Classifier: Topic :: Documentation
Classifier: Topic :: Utilities
Requires-Dist: Sphinx>=0.6
